hyperscript_cli/__init__.py
hyperscript_cli/__main__.py
hyperscript_cli/parser.py
hyperscript_cli-1.0.7.dist-info/LICENSE
hyperscript_cli-1.0.7.dist-info/METADATA
hyperscript_cli-1.0.7.dist-info/WHEEL
hyperscript_cli-1.0.7.dist-info/entry_points.txt
hyperscript_cli-1.0.7.dist-info/top_level.txt
hyperscript_cli-1.0.7.dist-info/RECORD
