Metadata-Version: 2.1
Name: hyperscript-cli
Version: 1.0.7
Summary: Powerful HTTP Request Tester
Home-page: https://github.com/happer64bit/hyperscript
Author: Happer
Author-email: happer64bit@gmail.com
Keywords: configuration requests API handling
Classifier: Development Status :: 4 - Beta
Classifier: Intended Audience :: Developers
Classifier: License :: OSI Approved :: MIT License
Classifier: Programming Language :: Python :: 3
Classifier: Programming Language :: Python :: 3.8
Classifier: Programming Language :: Python :: 3.9
Classifier: Programming Language :: Python :: 3.10
Classifier: Programming Language :: Python :: 3.11
Classifier: Programming Language :: Python :: 3.12
Classifier: Programming Language :: Python :: Implementation :: CPython
Classifier: Programming Language :: Python :: Implementation :: PyPy
Requires-Python: >=3.8
License-File: LICENSE
Requires-Dist: requests
Requires-Dist: colorama
